kustomize_file/__init__.py
kustomize_file/main.py
kustomize_file-0.0.5.dist-info/entry_points.txt
kustomize_file-0.0.5.dist-info/LICENSE
kustomize_file-0.0.5.dist-info/WHEEL
kustomize_file-0.0.5.dist-info/METADATA
kustomize_file-0.0.5.dist-info/RECORD
